{
  "video_id": "video6350",
  "summary": "a person is stirring some food into a pot",
  "scene_captions": [
    {
      "start_time": 1,
      "end_time": 2,
      "caption": "a person stirring noodles in a pot"
    },
    {
      "start_time": 2,
      "end_time": 13,
      "caption": "a person is stirring some food into a pot"
    },
    {
      "start_time": 13,
      "end_time": 17,
      "caption": "a person is cooking some food on the stove"
    },
    {
      "start_time": 17,
      "end_time": 18,
      "caption": "a person is pouring soup into a pot"
    },
    {
      "start_time": 18,
      "end_time": 20,
      "caption": "a person is cooking some food on the stove"
    },
    {
      "start_time": 20,
      "end_time": 22,
      "caption": "a person is pouring soup into a pot"
    }
  ]
}