{
  "video_id": "video5650",
  "summary": "a group of people in costumes and masks",
  "scene_captions": [
    {
      "start_time": 0,
      "end_time": 1,
      "caption": "a group of people in costumes and masks"
    },
    {
      "start_time": 1,
      "end_time": 6,
      "caption": "a man in a black jacket and sunglasses standing in front of a wall with egyptian statues"
    },
    {
      "start_time": 6,
      "end_time": 7,
      "caption": "a man in a black jacket and gold headdre smoking a cigarette"
    },
    {
      "start_time": 7,
      "end_time": 8,
      "caption": "a man in a suit and a woman in a costume"
    },
    {
      "start_time": 8,
      "end_time": 9,
      "caption": "a man in a gold mask with his hands on his chest"
    },
    {
      "start_time": 9,
      "end_time": 10,
      "caption": "a woman in a white dress and gold necklaces"
    }
  ]
}