{
  "video_id": "video6590",
  "summary": "a group of people standing on top of a field",
  "scene_captions": [
    {
      "start_time": 0,
      "end_time": 2,
      "caption": "a man in a blue and white uniform holding a football ball"
    },
    {
      "start_time": 2,
      "end_time": 4,
      "caption": "a group of people standing on a field"
    },
    {
      "start_time": 4,
      "end_time": 6,
      "caption": "a crowd of people holding up a box"
    },
    {
      "start_time": 6,
      "end_time": 8,
      "caption": "a group of people standing on a field"
    },
    {
      "start_time": 8,
      "end_time": 9,
      "caption": "a crowd of people are cheering at a football game"
    },
    {
      "start_time": 9,
      "end_time": 10,
      "caption": "a group of people standing on top of a field"
    }
  ]
}