{
  "video_id": "video6140",
  "summary": "a group of people dancing in a room",
  "scene_captions": [
    {
      "start_time": 0,
      "end_time": 1,
      "caption": "a man in a tuxed"
    },
    {
      "start_time": 1,
      "end_time": 2,
      "caption": "a crowd of people sitting in a theater"
    },
    {
      "start_time": 2,
      "end_time": 5,
      "caption": "a crowd of people"
    },
    {
      "start_time": 6,
      "end_time": 8,
      "caption": "a man in a tuxed"
    },
    {
      "start_time": 8,
      "end_time": 9,
      "caption": "a group of people"
    },
    {
      "start_time": 9,
      "end_time": 10,
      "caption": "a man in a tuxed"
    },
    {
      "start_time": 10,
      "end_time": 14,
      "caption": "a group of people dancing in a room"
    },
    {
      "start_time": 14,
      "end_time": 15,
      "caption": "a crowd of people"
    },
    {
      "start_time": 15,
      "end_time": 16,
      "caption": "a group of people dancing on a dance floor"
    },
    {
      "start_time": 16,
      "end_time": 18,
      "caption": "a man in a tuxed suit"
    },
    {
      "start_time": 18,
      "end_time": 19,
      "caption": "a group of people dancing in a room"
    },
    {
      "start_time": 19,
      "end_time": 20,
      "caption": "a man in a tuxed"
    },
    {
      "start_time": 20,
      "end_time": 21,
      "caption": "a man and woman dancing on a red carpet"
    },
    {
      "start_time": 21,
      "end_time": 22,
      "caption": "a group of people dancing"
    },
    {
      "start_time": 22,
      "end_time": 24,
      "caption": "a crowd of people"
    },
    {
      "start_time": 24,
      "end_time": 29,
      "caption": "a man in a tuxed"
    }
  ]
}