{
  "video_id": "video7220",
  "summary": "the voice - season 2 - episode 2 - the voice - episode 2 - the voice - episode 2",
  "scene_captions": [
    {
      "start_time": 0,
      "end_time": 2,
      "caption": "a man sitting in a red chair"
    },
    {
      "start_time": 3,
      "end_time": 4,
      "caption": "the voice - episode 2"
    },
    {
      "start_time": 5,
      "end_time": 10,
      "caption": "a young girl singing into a microphone"
    },
    {
      "start_time": 10,
      "end_time": 13,
      "caption": "the voice - season 2 - episode 2 - the voice - episode 2"
    }
  ]
}