{
  "video_id": "video7135",
  "summary": "a man in a green shirt is playing a dj",
  "scene_captions": [
    {
      "start_time": 1,
      "end_time": 3,
      "caption": "a man is in the middle of a tunnel"
    },
    {
      "start_time": 3,
      "end_time": 4,
      "caption": "a group of people on stage with lights"
    },
    {
      "start_time": 4,
      "end_time": 5,
      "caption": "a man in a red shirt is dancing"
    },
    {
      "start_time": 5,
      "end_time": 6,
      "caption": "a man doing a trick on a skateboard"
    },
    {
      "start_time": 6,
      "end_time": 7,
      "caption": "a man in a black shirt is holding a cell"
    },
    {
      "start_time": 7,
      "end_time": 8,
      "caption": "a man in a green shirt is playing a dj"
    },
    {
      "start_time": 8,
      "end_time": 9,
      "caption": "a man with a beard and a hat on"
    },
    {
      "start_time": 9,
      "end_time": 10,
      "caption": "a man in a green shirt playing a dj"
    },
    {
      "start_time": 10,
      "end_time": 11,
      "caption": "a man in a tank top shirt holding a pair of drums"
    },
    {
      "start_time": 11,
      "end_time": 12,
      "caption": "a group of people standing in a dark room"
    },
    {
      "start_time": 12,
      "end_time": 13,
      "caption": "a man in a black tank top standing in front of a crowd"
    },
    {
      "start_time": 13,
      "end_time": 14,
      "caption": "a group of people standing in a dark room"
    }
  ]
}