{
  "video_id": "video6799",
  "summary": "a large crowd of people are gathered in a large crowd at a music festival",
  "scene_captions": [
    {
      "start_time": 0,
      "end_time": 1,
      "caption": "a woman singing into a microphone"
    },
    {
      "start_time": 1,
      "end_time": 4,
      "caption": "a man sitting on a stage with a drum"
    },
    {
      "start_time": 4,
      "end_time": 5,
      "caption": "a large crowd of people at a music festival"
    },
    {
      "start_time": 6,
      "end_time": 8,
      "caption": "a crowd of people are gathered in a large crowd"
    },
    {
      "start_time": 9,
      "end_time": 10,
      "caption": "a woman standing on a stage with her hands up"
    },
    {
      "start_time": 10,
      "end_time": 11,
      "caption": "two men are playing guitars on stage"
    }
  ]
}