{
  "video_id": "video6062",
  "summary": "a man in a black shirt is singing into a microphone",
  "scene_captions": [
    {
      "start_time": 0,
      "end_time": 1,
      "caption": "the crowd at the concert"
    },
    {
      "start_time": 3,
      "end_time": 5,
      "caption": "a man in a black shirt is singing into a microphone"
    },
    {
      "start_time": 6,
      "end_time": 10,
      "caption": "the voice contestant is seen in this image"
    },
    {
      "start_time": 10,
      "end_time": 11,
      "caption": "a man in a suit and tie is singing into a microphone"
    }
  ]
}