{
  "video_id": "video6674",
  "summary": "a man in a white chef ' s hat and glasses is preparing food",
  "scene_captions": [
    {
      "start_time": 0,
      "end_time": 1,
      "caption": "a person is stirring a sauce into a pot"
    },
    {
      "start_time": 1,
      "end_time": 2,
      "caption": "a person is putting a piece of meat into a bowl"
    },
    {
      "start_time": 2,
      "end_time": 12,
      "caption": "a man in a white chef ' s hat and glasses is preparing food"
    }
  ]
}